LabFile/Lab2/Advance/lab2_adv_1.v
`timescale 1ns/1ps

module lab2_adv_1 (
    input clk,
    input rst,
    input [8:0] clause_1,
    input [8:0] clause_2,
    input [8:0] clause_3,
    input [8:0] clause_4,
    output reg satisfaction,
    output reg [2:0] out
);

    integer i;
    reg [2:0] assign_val;
    reg found;

    // function: evaluate one literal given assignment
    function eval_lit;
        input [2:0] lit;      // literal encoding
        input [2:0] val;      // {A,B,C}
        begin
            case(lit)
                3'b000: eval_lit = val[0];     // A
                3'b100: eval_lit = ~val[0];    // ~A
                3'b001: eval_lit = val[1];     // B
                3'b101: eval_lit = ~val[1];    // ~B
                3'b010: eval_lit = val[2];     // C
                3'b110: eval_lit = ~val[2];    // ~C
                default: eval_lit = 1'b0;      // invalid literal = false
            endcase            
        end
    endfunction

    // function: evaluate one clause
    function eval_clause;
        input [8:0] clause;
        input [2:0] val;
        reg l1, l2, l3;
        begin
            l1 = eval_lit(clause[8:6], val);
            l2 = eval_lit(clause[5:3], val);
            l3 = eval_lit(clause[2:0], val);
            eval_clause = l1 | l2 | l3;
            
            // display the clauses and the return result as
            // Clause %d, with each literal %s, %s, %s and assignment %b: result=%b
            $display("Clause %b, with literals %s, %s, %s and assignment %b: result=%b", clause, 
                (clause[8:6] == 3'b000) ? "A"  : (clause[8:6] == 3'b100) ? "~A" :
                (clause[8:6] == 3'b001) ? "B"  : (clause[8:6] == 3'b101) ? "~B" :
                (clause[8:6] == 3'b010) ? "C"  : (clause[8:6] == 3'b110) ? "~C" : "Invalid",

                (clause[5:3] == 3'b000) ? "A"  : (clause[5:3] == 3'b100) ? "~A" :
                (clause[5:3] == 3'b001) ? "B"  : (clause[5:3] == 3'b101) ? "~B" :
                (clause[5:3] == 3'b010) ? "C"  : (clause[5:3] == 3'b110) ? "~C" : "Invalid",

                (clause[2:0] == 3'b000) ? "A"  : (clause[2:0] == 3'b100) ? "~A" :
                (clause[2:0] == 3'b001) ? "B"  : (clause[2:0] == 3'b101) ? "~B" :
                (clause[2:0] == 3'b010) ? "C"  : (clause[2:0] == 3'b110) ? "~C" : "Invalid",
                val, eval_clause
            );
        end        
    endfunction

    // 新增暫存變數
    reg [2:0] temp_out;
    reg temp_satisfaction;

    always @(posedge clk) begin
        if (rst) begin
            satisfaction <= 0;
            out <= 3'b000;
        end else begin
            temp_satisfaction = 0;
            temp_out = 3'b111;
            found = 0;  

            for (i = 0; i < 8 && !found; i = i + 1) begin
                assign_val = i[2:0];
                if (eval_clause(clause_1, assign_val) &&
                    eval_clause(clause_2, assign_val) &&
                    eval_clause(clause_3, assign_val) &&
                    eval_clause(clause_4, assign_val) ) begin
                    temp_out = assign_val;      
                    temp_satisfaction = 1;
                    found = 1;       
                    $display("Found satisfying assignment %b", temp_out);
                end else begin
                    // do nothing, try next assignment
                    // display the assignment tried
                    $display("Tried assignment %b: not satisfied", assign_val);
                end
            end

            out <= temp_out;
            satisfaction <= temp_satisfaction;
        end
    end

endmodule

LabFile/Lab2/Advance/lab2_adv_1_t.v
`timescale 1ns/1ps

module lab2_adv_1_t;

    reg clk;
    reg rst;
    reg [8:0] clause_1, clause_2, clause_3, clause_4;
    wire [2:0] out;
    wire satisfaction;


    // Clock generation: 10 ns period
    initial clk = 1;
    always #5 clk = ~clk;

    //================================================
    // TODO1
    // Connect your lab2_adv_1 module here 
    // Please connect it by port name but not order
    lab2_adv_1 mod(
        .clk(clk),
        .rst(rst),
        .clause_1(clause_1),
        .clause_2(clause_2),
        .clause_3(clause_3),
        .clause_4(clause_4),
        .satisfaction(satisfaction),
        .out(out)
    );
    //================================================


    // TODO 2
    //you should test these 8 cases:
    //Test 0:
    //clause_1 = 9'b000_001_010;
    //clause_2 = 9'b100_101_110;
    //clause_3 = 9'b000_101_110;
    //clause_4 = 9'b100_001_010;

    //Test 1:
    //clause_1 = 9'b000_000_000;
    //clause_2 = 9'b100_100_100;
    //clause_3 = 9'b001_001_001;
    //clause_4 = 9'b101_101_101;

    //Test 2:
    //clause_1 = 9'b010_010_010;
    //clause_2 = 9'b110_110_110;
    //clause_3 = 9'b000_001_010;
    //clause_4 = 9'b100_101_110;

    //Test 3:
    //clause_1 = 9'b000_101_100; 
    //clause_2 = 9'b010_010_010;
    //clause_3 = 9'b100_101_010;
    //clause_4 = 9'b000_001_110;

    //Test 4:
    //clause_1 = 9'b000_101_110; 
    //clause_2 = 9'b100_001_010; 
    //clause_3 = 9'b001_110_000; 
    //clause_4 = 9'b101_010_100; 

    //Test 5:
    //clause_1 = 9'b000_000_000;
    //clause_2 = 9'b100_100_100;
    //clause_3 = 9'b001_001_001;
    //clause_4 = 9'b101_101_101;

    //Test 6:
    //clause_1 = 9'b010_001_000;
    //clause_2 = 9'b001_100_010; 
    //clause_3 = 9'b000_101_010;
    //clause_4 = 9'b100_101_010; 

    //Test 7:
    //clause_1 = 9'b000_000_001; 
    //clause_2 = 9'b001_001_010; 
    //clause_3 = 9'b010_010_000; 
    //clause_4 = 9'b100_101_110; 
        
    


    //================================================

    // TODO 3
    //write some code here to change the input of the moudle above
    integer i;  // test index

    initial begin
        @(negedge clk); // let rst signal start at 15ns
        @(negedge clk);
        rst = 1;
        clause_1 = 0; clause_2 = 0; clause_3 = 0; clause_4 = 0;
        @(negedge clk);
        @(negedge clk); // let rst signal work for 20ns
        rst = 0;

        for (i = 0; i < 8; i = i + 1) begin
            clause_1 = 0; clause_2 = 0; clause_3 = 0; clause_4 = 0;
            rst = 0;
            
            case (i)
                0: begin
                    clause_1 = 9'b000_001_010;
                    clause_2 = 9'b100_101_110;
                    clause_3 = 9'b000_101_110;
                    clause_4 = 9'b100_001_010;
                end
                1: begin
                    clause_1 = 9'b000_000_000;
                    clause_2 = 9'b100_100_100;
                    clause_3 = 9'b001_001_001;
                    clause_4 = 9'b101_101_101;
                end
                2: begin
                    clause_1 = 9'b010_010_010;
                    clause_2 = 9'b110_110_110;
                    clause_3 = 9'b000_001_010;
                    clause_4 = 9'b100_101_110;
                end
                3: begin
                    //clause_1 = 9'b000_101_100; 
    //clause_2 = 9'b010_010_010;
    //clause_3 = 9'b100_101_010;
    //clause_4 = 9'b000_001_110;
                    clause_1 = 9'b000_101_100; 
                    clause_2 = 9'b010_010_010;
                    clause_3 = 9'b100_101_010;
                    clause_4 = 9'b000_001_110;
                end
                4: begin
                    //clause_1 = 9'b000_101_110; 
    //clause_2 = 9'b100_001_010; 
    //clause_3 = 9'b001_110_000; 
    //clause_4 = 9'b101_010_100; 
                    clause_1 = 9'b000_101_110; 
                    clause_2 = 9'b100_001_010; 
                    clause_3 = 9'b001_110_000; 
                    clause_4 = 9'b101_010_100;
                end
                5: begin
                    //clause_1 = 9'b000_000_000;
    //clause_2 = 9'b100_100_100;
    //clause_3 = 9'b001_001_001;
    //clause_4 = 9'b101_101_101;
                    clause_1 = 9'b000_000_000;
                    clause_2 = 9'b100_100_100;
                    clause_3 = 9'b001_001_001;
                    clause_4 = 9'b101_101_101;
                end
                6: begin
                    //clause_1 = 9'b010_001_000;
    //clause_2 = 9'b001_100_010; 
    //clause_3 = 9'b000_101_010;
    //clause_4 = 9'b100_101_010; 
                    clause_1 = 9'b010_001_000;
                    clause_2 = 9'b001_100_010; 
                    clause_3 = 9'b000_101_010;
                    clause_4 = 9'b100_101_010;
                end
                7: begin
                    clause_1 = 9'b000_000_001; 
                    clause_2 = 9'b001_001_010; 
                    clause_3 = 9'b010_010_000; 
                    clause_4 = 9'b100_101_110;
                end
            endcase

            @(negedge clk); // wait for a clock cycle
        end
        @(posedge clk); // let simulation run til 120000ns.
        $display("All test cases done.");
        $finish;
    end
    
    
    //================================================


endmodule

Vivado/Lab2/Lab2Adv/Lab2Adv.sim/sim_1/behav/xsim/lab2_adv_1_t.vcd
$date
   Sat Sep 20 23:43:17 2025
$end
$version
  2019.2
$end
$timescale
  1ps
$end
$scope module lab2_adv_1_t $end
$var reg 1 ! clk $end
$var reg 1 " rst $end
$var reg 9 # clause_1 [8:0] $end
$var reg 9 $ clause_2 [8:0] $end
$var reg 9 % clause_3 [8:0] $end
$var reg 9 & clause_4 [8:0] $end
$var wire 3 ' out [2:0] $end
$var wire 1 ( satisfaction $end
$var integer 32 ) i $end
$scope module mod $end
$var wire 1 * clk $end
$var wire 1 + rst $end
$var wire 9 , clause_1 [8:0] $end
$var wire 9 - clause_2 [8:0] $end
$var wire 9 . clause_3 [8:0] $end
$var wire 9 / clause_4 [8:0] $end
$var reg 1 0 satisfaction $end
$var reg 3 1 out [2:0] $end
$var integer 32 2 i $end
$var reg 3 3 assign_val [2:0] $end
$var reg 1 4 found $end
$var reg 3 5 temp_out [2:0] $end
$var reg 1 6 temp_satisfaction $end
$scope function eval_lit $end
$var reg 1 7 eval_lit $end
$var reg 3 8 lit [2:0] $end
$var reg 3 9 val [2:0] $end
$upscope $end
$scope function eval_clause $end
$var reg 1 : eval_clause $end
$var reg 9 ; clause [8:0] $end
$var reg 3 < val [2:0] $end
$var reg 1 = l1 $end
$var reg 1 > l2 $end
$var reg 1 ? l3 $end
$upscope $end
$upscope $end
$upscope $end
$enddefinitions $end
#0
$dumpvars
1!
x"
bx #
bx $
bx %
bx &
b0 '
0(
bx )
1*
x+
bx ,
bx -
bx .
bx /
00
b0 1
b1000 2
b111 3
04
b0 5
06
07
bx 8
b111 9
0:
bx ;
b111 <
0=
0>
0?
$end
#5000
0!
0*
#10000
1!
1*
b1000 2
b111 3
b111 9
b111 <
#15000
0!
1"
b0 #
b0 $
b0 %
b0 &
0*
1+
b0 ,
b0 -
b0 .
b0 /
#20000
1!
1*
#25000
0!
0*
#30000
1!
1*
#35000
0!
0"
b1010 #
b100101110 $
b101110 %
b100001010 &
b0 )
0*
0+
b1010 ,
b100101110 -
b101110 .
b100001010 /
#40000
1!
b1 '
1(
1*
10
b1 1
b10 2
b1 3
14
b1 5
16
17
b10 8
b1 9
1:
b100001010 ;
b1 <
1=
0>
1?
#45000
0!
b0 #
b100100100 $
b1001001 %
b101101101 &
b1 )
0*
b0 ,
b100100100 -
b1001001 .
b101101101 /
#50000
1!
b0 '
0(
1*
00
b0 1
b1000 2
b111 3
04
b0 5
06
07
b100 8
b111 9
0:
b100100100 ;
b111 <
0=
0>
0?
#55000
0!
b10010010 #
b110110110 $
b1010 %
b100101110 &
b10 )
0*
b10010010 ,
b110110110 -
b1010 .
b100101110 /
#60000
1!
1*
b1000 2
b111 3
07
b110 8
b111 9
0:
b110110110 ;
b111 <
0=
0>
0?
#65000
0!
b101100 #
b10010010 $
b100101010 %
b1110 &
b11 )
0*
b101100 ,
b10010010 -
b100101010 .
b1110 /
#70000
1!
b11 '
1(
1*
10
b11 1
b100 2
b11 3
14
b11 5
16
07
b110 8
b11 9
1:
b1110 ;
b11 <
0=
1>
0?
#75000
0!
b101110 #
b100001010 $
b1110000 %
b101010100 &
b100 )
0*
b101110 ,
b100001010 -
b1110000 .
b101010100 /
#80000
1!
b0 '
1*
b0 1
b1 2
b0 3
14
b0 5
16
17
b100 8
b0 9
b101010100 ;
b0 <
1=
0>
1?
#85000
0!
b0 #
b100100100 $
b1001001 %
b101101101 &
b101 )
0*
b0 ,
b100100100 -
b1001001 .
b101101101 /
#90000
1!
0(
1*
00
b1000 2
b111 3
04
06
07
b100 8
b111 9
0:
b100100100 ;
b111 <
0=
0>
0?
#95000
0!
b10001000 #
b1100010 $
b101010 %
b100101010 &
b110 )
0*
b10001000 ,
b1100010 -
b101010 .
b100101010 /
#100000
1!
b1 '
1(
1*
10
b1 1
b10 2
b1 3
14
b1 5
16
17
b10 8
b1 9
1:
b100101010 ;
b1 <
1=
1>
1?
#105000
0!
b1 #
b1001010 $
b10010000 %
b100101110 &
b111 )
0*
b1 ,
b1001010 -
b10010000 .
b100101110 /
#110000
1!
b11 '
1*
b11 1
b100 2
b11 3
14
b11 5
16
07
b110 8
b11 9
1:
b100101110 ;
b11 <
1=
0>
0?
#115000
0!
b1000 )
0*
