LabFile/Lab3/Test_Report/test_report.v
`timescale 1ns/1ps

//===========================================================
//  One Pulse Demonstration
//===========================================================
module one_pulse_demo (
    input wire clk_fsm,
    input wire clk_fast,
    input wire clk_slow,
    input wire btn_raw,
    output reg fsm_trigger_correct,
    output reg fsm_trigger_fast,
    output reg fsm_trigger_slow
);
    // Debounce 模擬：直接延遲一下 (簡化)
    reg btn_debounced;
    always @(posedge clk_fsm) begin
        btn_debounced <= btn_raw;
    end

    //=============================
    // Case 1: 正確 one pulse (同時脈)
    //=============================
    reg btn_d1;
    wire pulse_correct;
    always @(posedge clk_fsm) btn_d1 <= btn_debounced;
    assign pulse_correct = btn_debounced & ~btn_d1;

    always @(posedge clk_fsm)
        if (pulse_correct)
            fsm_trigger_correct <= 1'b1;
        else
            fsm_trigger_correct <= 1'b0;

    //=============================
    // Case 2: One pulse 過快 (fast clock)
    //=============================
    reg btn_d2;
    wire pulse_fast;
    always @(posedge clk_fast) btn_d2 <= btn_debounced;
    assign pulse_fast = btn_debounced & ~btn_d2;

    always @(posedge clk_fsm)
        if (pulse_fast)
            fsm_trigger_fast <= 1'b1;
        else
            fsm_trigger_fast <= 1'b0;

    //=============================
    // Case 3: One pulse 過慢 (slow clock)
    //=============================
    reg btn_d3;
    wire pulse_slow;
    always @(posedge clk_slow) btn_d3 <= btn_debounced;
    assign pulse_slow = btn_debounced & ~btn_d3;

    always @(posedge clk_fsm)
        if (pulse_slow)
            fsm_trigger_slow <= 1'b1;
        else
            fsm_trigger_slow <= 1'b0;
endmodule


//===========================================================
//  Testbench
//===========================================================
module tb_one_pulse_demo;
    reg clk_fsm = 0;
    reg clk_fast = 0;
    reg clk_slow = 0;
    reg btn_raw = 0;

    wire fsm_trigger_correct;
    wire fsm_trigger_fast;
    wire fsm_trigger_slow;

    // Instantiate DUT
    one_pulse_demo uut (
        .clk_fsm(clk_fsm),
        .clk_fast(clk_fast),
        .clk_slow(clk_slow),
        .btn_raw(btn_raw),
        .fsm_trigger_correct(fsm_trigger_correct),
        .fsm_trigger_fast(fsm_trigger_fast),
        .fsm_trigger_slow(fsm_trigger_slow)
    );

    // Clock generation
    always #10 clk_fsm = ~clk_fsm;  // FSM clock = 50 MHz
    always #5  clk_fast = ~clk_fast; // Fast clock = 100 MHz
    always #20 clk_slow = ~clk_slow; // Slow clock = 25 MHz

    // Stimulus
    initial begin
        $dumpfile("one_pulse_demo.vcd");
        $dumpvars(0, tb_one_pulse_demo);

        btn_raw = 0;
        #50;

        // 第一次按下（長按）
        btn_raw = 1; #100;
        btn_raw = 0; #200;

        // 第二次（短按）
        btn_raw = 1; #50;
        btn_raw = 0; #150;

        // 第三次（長按）
        btn_raw = 1; #120;
        btn_raw = 0; #180;

        // 第四次（非常短按）
        btn_raw = 1; #30;
        btn_raw = 0; #150;

        // 第五次（長按）
        btn_raw = 1; #200;
        btn_raw = 0; #200;

        // 第六次（短按）
        btn_raw = 1; #60;
        btn_raw = 0; #300;

        // 結束模擬
        #1000;
        $finish;
    end
endmodule

Vivado/Lab3/Report/Report.sim/sim_1/behav/xsim/one_pulse_demo.vcd
$date
   Fri Oct 10 01:33:41 2025
$end
$version
  2019.2
$end
$timescale
  1ps
$end
$scope module tb_one_pulse_demo $end
$var reg 1 ! clk_fsm $end
$var reg 1 " clk_fast $end
$var reg 1 # clk_slow $end
$var reg 1 $ btn_raw $end
$var wire 1 % fsm_trigger_correct $end
$var wire 1 & fsm_trigger_fast $end
$var wire 1 ' fsm_trigger_slow $end
$scope module uut $end
$var wire 1 ( clk_fsm $end
$var wire 1 ) clk_fast $end
$var wire 1 * clk_slow $end
$var wire 1 + btn_raw $end
$var reg 1 , fsm_trigger_correct $end
$var reg 1 - fsm_trigger_fast $end
$var reg 1 . fsm_trigger_slow $end
$var reg 1 / btn_debounced $end
$var reg 1 0 btn_d1 $end
$var wire 1 1 pulse_correct $end
$var reg 1 2 btn_d2 $end
$var wire 1 3 pulse_fast $end
$var reg 1 4 btn_d3 $end
$var wire 1 5 pulse_slow $end
$upscope $end
$upscope $end
$enddefinitions $end
#0
$dumpvars
0!
0"
0#
0$
x%
x&
x'
0(
0)
0*
0+
x,
x-
x.
x/
x0
x1
x2
x3
x4
x5
$end
#5000
1"
1)
#10000
1!
0"
0%
0&
0'
1(
0)
0,
0-
0.
0/
01
03
05
#15000
1"
1)
02
#20000
0!
0"
1#
0(
0)
1*
04
#25000
1"
1)
#30000
1!
0"
1(
0)
00
#35000
1"
1)
#40000
0!
0"
0#
0(
0)
0*
#45000
1"
1)
#50000
1!
0"
1$
1(
0)
1+
1/
11
13
15
#55000
1"
1)
12
03
#60000
0!
0"
1#
0(
0)
1*
14
05
#65000
1"
1)
#70000
1!
0"
1%
1(
0)
1,
10
01
#75000
1"
1)
#80000
0!
0"
0#
0(
0)
0*
#85000
1"
1)
#90000
1!
0"
0%
1(
0)
0,
#95000
1"
1)
#100000
0!
0"
1#
0(
0)
1*
#105000
1"
1)
#110000
1!
0"
1(
0)
#115000
1"
1)
#120000
0!
0"
0#
0(
0)
0*
#125000
1"
1)
#130000
1!
0"
1(
0)
#135000
1"
1)
#140000
0!
0"
1#
0(
0)
1*
#145000
1"
1)
#150000
1!
0"
0$
1(
0)
0+
0/
#155000
1"
1)
02
#160000
0!
0"
0#
0(
0)
0*
#165000
1"
1)
#170000
1!
0"
1(
0)
00
#175000
1"
1)
#180000
0!
0"
1#
0(
0)
1*
04
#185000
1"
1)
#190000
1!
0"
1(
0)
#195000
1"
1)
#200000
0!
0"
0#
0(
0)
0*
#205000
1"
1)
#210000
1!
0"
1(
0)
#215000
1"
1)
#220000
0!
0"
1#
0(
0)
1*
#225000
1"
1)
#230000
1!
0"
1(
0)
#235000
1"
1)
#240000
0!
0"
0#
0(
0)
0*
#245000
1"
1)
#250000
1!
0"
1(
0)
#255000
1"
1)
#260000
0!
0"
1#
0(
0)
1*
#265000
1"
1)
#270000
1!
0"
1(
0)
#275000
1"
1)
#280000
0!
0"
0#
0(
0)
0*
#285000
1"
1)
#290000
1!
0"
1(
0)
#295000
1"
1)
#300000
0!
0"
1#
0(
0)
1*
#305000
1"
1)
#310000
1!
0"
1(
0)
#315000
1"
1)
#320000
0!
0"
0#
0(
0)
0*
#325000
1"
1)
#330000
1!
0"
1(
0)
#335000
1"
1)
#340000
0!
0"
1#
0(
0)
1*
#345000
1"
1)
#350000
1!
0"
1$
1(
0)
1+
1/
11
13
15
#355000
1"
1)
12
03
#360000
0!
0"
0#
0(
0)
0*
#365000
1"
1)
#370000
1!
0"
1%
1'
1(
0)
1,
1.
10
01
#375000
1"
1)
#380000
0!
0"
1#
0(
0)
1*
14
05
#385000
1"
1)
#390000
1!
0"
0%
0'
1(
0)
0,
0.
#395000
1"
1)
#400000
0!
0"
0#
0$
0(
0)
0*
0+
#405000
1"
1)
#410000
1!
0"
1(
0)
0/
#415000
1"
1)
02
#420000
0!
0"
1#
0(
0)
1*
04
#425000
1"
1)
#430000
1!
0"
1(
0)
00
#435000
1"
1)
#440000
0!
0"
0#
0(
0)
0*
#445000
1"
1)
#450000
1!
0"
1(
0)
#455000
1"
1)
#460000
0!
0"
1#
0(
0)
1*
#465000
1"
1)
#470000
1!
0"
1(
0)
#475000
1"
1)
#480000
0!
0"
0#
0(
0)
0*
#485000
1"
1)
#490000
1!
0"
1(
0)
#495000
1"
1)
#500000
0!
0"
1#
0(
0)
1*
#505000
1"
1)
#510000
1!
0"
1(
0)
#515000
1"
1)
#520000
0!
0"
0#
0(
0)
0*
#525000
1"
1)
#530000
1!
0"
1(
0)
#535000
1"
1)
#540000
0!
0"
1#
0(
0)
1*
#545000
1"
1)
#550000
1!
0"
1$
1(
0)
1+
1/
11
13
15
#555000
1"
1)
12
03
#560000
0!
0"
0#
0(
0)
0*
#565000
1"
1)
#570000
1!
0"
1%
1'
1(
0)
1,
1.
10
01
#575000
1"
1)
#580000
0!
0"
1#
0(
0)
1*
14
05
#585000
1"
1)
#590000
1!
0"
0%
0'
1(
0)
0,
0.
#595000
1"
1)
#600000
0!
0"
0#
0(
0)
0*
#605000
1"
1)
#610000
1!
0"
1(
0)
#615000
1"
1)
#620000
0!
0"
1#
0(
0)
1*
#625000
1"
1)
#630000
1!
0"
1(
0)
#635000
1"
1)
#640000
0!
0"
0#
0(
0)
0*
#645000
1"
1)
#650000
1!
0"
1(
0)
#655000
1"
1)
#660000
0!
0"
1#
0(
0)
1*
#665000
1"
1)
#670000
1!
0"
0$
1(
0)
0+
0/
#675000
1"
1)
02
#680000
0!
0"
0#
0(
0)
0*
#685000
1"
1)
#690000
1!
0"
1(
0)
00
#695000
1"
1)
#700000
0!
0"
1#
0(
0)
1*
04
#705000
1"
1)
#710000
1!
0"
1(
0)
#715000
1"
1)
#720000
0!
0"
0#
0(
0)
0*
#725000
1"
1)
#730000
1!
0"
1(
0)
#735000
1"
1)
#740000
0!
0"
1#
0(
0)
1*
#745000
1"
1)
#750000
1!
0"
1(
0)
#755000
1"
1)
#760000
0!
0"
0#
0(
0)
0*
#765000
1"
1)
#770000
1!
0"
1(
0)
#775000
1"
1)
#780000
0!
0"
1#
0(
0)
1*
#785000
1"
1)
#790000
1!
0"
1(
0)
#795000
1"
1)
#800000
0!
0"
0#
0(
0)
0*
#805000
1"
1)
#810000
1!
0"
1(
0)
#815000
1"
1)
#820000
0!
0"
1#
0(
0)
1*
#825000
1"
1)
#830000
1!
0"
1(
0)
#835000
1"
1)
#840000
0!
0"
0#
0(
0)
0*
#845000
1"
1)
#850000
1!
0"
1$
1(
0)
1+
1/
11
13
15
#855000
1"
1)
12
03
#860000
0!
0"
1#
0(
0)
1*
14
05
#865000
1"
1)
#870000
1!
0"
1%
1(
0)
1,
10
01
#875000
1"
1)
#880000
0!
0"
0#
0$
0(
0)
0*
0+
#885000
1"
1)
#890000
1!
0"
0%
1(
0)
0,
0/
#895000
1"
1)
02
#900000
0!
0"
1#
0(
0)
1*
04
#905000
1"
1)
#910000
1!
0"
1(
0)
00
